azure_deploy_cli/__init__.py
azure_deploy_cli/_version.py
azure_deploy_cli/cli.py
azure_deploy_cli/py.typed
azure_deploy_cli/aca/aca_cli.py
azure_deploy_cli/aca/deploy_aca.py
azure_deploy_cli/aca/model.py
azure_deploy_cli/aca/yaml_loader.py
azure_deploy_cli/aca/bash/aca-cert/create.sh
azure_deploy_cli/aca/bash/aca-cert/destroy.sh
azure_deploy_cli/identity/__init__.py
azure_deploy_cli/identity/group.py
azure_deploy_cli/identity/identity_cli.py
azure_deploy_cli/identity/managed_identity.py
azure_deploy_cli/identity/models.py
azure_deploy_cli/identity/py.typed
azure_deploy_cli/identity/role.py
azure_deploy_cli/identity/service_principal.py
azure_deploy_cli/utils/__init__.py
azure_deploy_cli/utils/azure_cli.py
azure_deploy_cli/utils/docker.py
azure_deploy_cli/utils/env.py
azure_deploy_cli/utils/key_vault.py
azure_deploy_cli/utils/logging.py
azure_deploy_cli/utils/py.typed
azure_deploy_cli-1.1.1.dist-info/licenses/LICENSE
azure_deploy_cli-1.1.1.dist-info/METADATA
azure_deploy_cli-1.1.1.dist-info/WHEEL
azure_deploy_cli-1.1.1.dist-info/entry_points.txt
azure_deploy_cli-1.1.1.dist-info/top_level.txt
azure_deploy_cli-1.1.1.dist-info/RECORD
