Metadata-Version: 2.4
Name: azure-deploy-cli
Version: 1.1.1
Summary: Python CLI for Azure deployment automation - identity, roles, and container apps management
Author-email: decewei <celinew1221@gmail.com>
License: Mozilla Public License Version 2.0
Project-URL: Homepage, https://github.com/decewei/azure-deploy-cli
Project-URL: Repository, https://github.com/decewei/azure-deploy-cli.git
Project-URL: Issues, https://github.com/decewei/azure-deploy-cli/issues
Keywords: azure,identity,roles,service-principal
Classifier: Development Status :: 3 - Alpha
Classifier: Intended Audience :: Developers
Classifier: License :: OSI Approved :: Mozilla Public License 2.0 (MPL 2.0)
Classifier: Natural Language :: English
Classifier: Programming Language :: Python :: 3
Classifier: Programming Language :: Python :: 3.11
Classifier: Programming Language :: Python :: 3.12
Requires-Python: >=3.11
License-File: LICENSE
Requires-Dist: azure-identity==1.25.1
Requires-Dist: azure-mgmt-appcontainers==4.0.0
Requires-Dist: azure-mgmt-authorization==4.0.0
Requires-Dist: azure-mgmt-keyvault==13.0.0
Requires-Dist: azure-mgmt-msi==7.1.0
Requires-Dist: python-dotenv==1.2.1
Requires-Dist: pydantic==2.12.5
Requires-Dist: PyYAML==6.0.3
Provides-Extra: dev
Requires-Dist: ruff==0.14.14; extra == "dev"
Requires-Dist: mypy==1.19.1; extra == "dev"
Requires-Dist: pytest==9.0.2; extra == "dev"
Requires-Dist: pytest-asyncio==1.3.0; extra == "dev"
Requires-Dist: coverage==7.13.2; extra == "dev"
Requires-Dist: pytest-cov==7.0.0; extra == "dev"
Requires-Dist: commitizen==4.12.1; extra == "dev"
Requires-Dist: pre-commit==4.5.1; extra == "dev"
Requires-Dist: types-setuptools==80.10.0.20260124; extra == "dev"
Requires-Dist: types-PyYAML==6.0.12.20250915; extra == "dev"
Dynamic: license-file
